MANIFEST.in
Makefile
README.rst
setup.py
kfreader/__init__.py
kfreader/core.py
kfreader/vendor/ArrayList.c
kfreader/vendor/ArrayList.h
kfreader/vendor/ArrayList.o
kfreader/vendor/KFReader.c
kfreader/vendor/KFReader.o
kfreader/vendor/KFc.h
kfreader/vendor/README.txt
kfreader_cffi.egg-info/PKG-INFO
kfreader_cffi.egg-info/SOURCES.txt
kfreader_cffi.egg-info/dependency_links.txt
kfreader_cffi.egg-info/not-zip-safe
kfreader_cffi.egg-info/requires.txt
kfreader_cffi.egg-info/top_level.txt