Metadata-Version: 1.1
Name: kfreader-cffi
Version: 0.2.3
Summary: Python bindings for KFReader, a library from the ADF computational chemistry package
Home-page: https://github.com/mstolyarchuk/kfreader-cffi
Author: Maxim Stolyarchuk
Author-email: maxim.stolyarchuk@gmail.com
License: UNKNOWN
Platform: UNKNOWN
Classifier: Development Status :: 4 - Beta
Classifier: Intended Audience :: Developers
Classifier: Intended Audience :: Science/Research
Classifier: License :: OSI Approved :: GNU Library or Lesser General Public License (LGPL)
Classifier: Programming Language :: Python
Classifier: Programming Language :: Python :: 3
Classifier: Topic :: Software Development :: Libraries :: Python Modules
